[
  {
    "kind": "eikon.catalog.entry",
    "schemaVersion": "1.0",
    "id": "liftaris/ares",
    "version": "1.0.0",
    "sourceKey": "registry:eikon.liftaris.dev:liftaris/ares@1.0.0",
    "name": "ares",
    "title": "ares",
    "author": "kaio",
    "glyph": "⚔",
    "poster": "⠿⢿⣦⣌⡻⣷⣟⢯⡈⢞⣿⣿⡯⣞⡧⣿⣵⣴⣶⣾⣿⣿⠿⠾⣦⣴⣼⣻⣿⣦⢹⡿⣣⣟⣾⣿⣿⣿⠄⠀⠀⠀⠀⠀⠀⠀⠀⠀\n⠀⠀⠈⠉⠹⠾⢿⢝⢳⣄⠫⣻⣷⣷⣿⡿⠟⣋⣽⣿⣿⣿⣶⣾⣶⣾⣿⣽⣿⡾⣟⡲⣼⡾⡿⣿⣿⢗⣿⡆⠀⠀⠀⠀⠀⠀⠀⠀\n⠀⠀⠀⠀⠀⠀⠀⢀⠑⣴⣿⣿⣿⢟⣽⣾⣿⣿⣿⠿⠿⢿⡛⠛⣿⣿⢿⢿⣿⣿⣮⣷⣽⢯⣾⡻⣟⣯⣯⠿⣆⠀⠀⠀⠀⠀⠀⠀\n⠀⠀⠀⠀⠀⠀⠀⠰⣬⡿⠟⢛⣥⣿⣿⣿⠟⣿⣶⣶⣾⣿⣿⣴⣿⣿⣾⣶⣭⡻⢿⣿⣿⡻⣝⣭⣿⣶⣾⣷⣤⣄⠀⠀⠀⠀⠀⠀\n⠀⠀⠀⠀⠀⠀⠀⠈⠁⢠⠀⠸⣿⣿⡿⣻⣶⣟⣿⣏⣿⢿⣭⣽⣿⣿⣿⣿⣯⣿⣮⠊⣿⣿⣿⣯⢕⣲⣾⣿⡿⢫⠀⠀⠀⠀⠀⠀\n⠀⠀⠀⠀⠀⠀⠀⠀⠀⠀⠀⠀⢻⣿⣾⣿⣿⣿⣿⣧⣿⣿⣿⣿⣿⣿⣿⣿⣿⣿⣿⣟⡟⢮⢿⡿⣯⣿⣿⣿⣿⣷⣢⠀⠀⠀⠀⠀\n⠀⠀⠀⠀⠀⠀⠀⠀⠀⡴⠃⢀⣾⣿⣿⣿⣿⣿⣿⢫⣿⣿⣿⣿⣿⣿⣿⣿⣿⣿⣿⣿⣿⣧⣄⠹⢿⡔⢿⣿⣿⡻⣿⡆⠀⠀⠀⠀\n⠀⠀⠀⠀⠀⠀⠀⠀⡼⠁⣄⣨⣭⣭⣭⣟⣛⣿⠿⢰⣾⣽⣷⣿⣿⣿⣿⣿⣿⣿⣿⣿⣿⣿⣿⣷⠉⣷⢿⣳⢿⣿⡪⡅⠀⠀⠀⠀\n⠀⠀⠀⠀⠀⠀⠀⢘⣵⣭⣷⣾⣿⣿⣿⣷⣾⣯⣝⡓⠧⣭⣻⣿⣿⣿⣿⣿⣿⣹⣟⣿⣿⣿⣿⣿⣷⡘⠉⣺⣄⣻⣻⣮⠆⠀⠀⠀\n⠀⠀⠀⠀⠀⠀⡔⢁⣿⣿⣿⣿⣿⣿⣿⣿⣿⣿⣿⣿⣿⣿⣿⣯⣾⣿⣽⣛⠿⠅⠿⣿⢿⣿⣿⣿⣿⣧⠄⢱⣫⢞⢽⣿⠧⠀⠀⠀\n⠀⠀⠀⠀⠀⠈⠄⢘⣿⣿⡿⣿⠿⠿⣿⡿⠿⠿⠿⠛⣿⣿⣿⣿⣿⣿⣿⣿⣿⣫⣷⣾⣿⢿⣿⣿⣿⣷⠅⠘⣡⣿⣍⣾⢿⡂⠀⠀\n⠀⠀⠀⠀⠀⠀⣃⡘⠛⢉⣶⣿⣿⣿⣿⠿⠶⣿⣿⣿⣿⣿⣷⣿⣟⣿⣻⣿⣿⠿⢿⣯⢟⣖⢺⣻⣿⣿⡃⢨⢤⢞⣿⣏⣷⣃⠀⠀\n⠀⠀⠀⢀⠠⠪⠊⢴⢾⣽⣿⣿⣏⣥⣷⠾⠟⠋⠉⠁⠀⠀⠀⠀⠀⠈⠉⣉⡩⢽⣏⡱⣼⡿⣡⣻⡿⣿⠃⠘⣴⣿⡞⣿⣩⢷⡀⠀\n⠀⣠⣰⣷⣶⣶⣶⡿⢿⠟⠛⠋⠉⠁⠀⠀⠀⠀⠀⠀⠀⠀⠀⠀⠀⠀⠀⣿⣷⣾⢿⡿⣟⣟⣾⣿⣿⣿⣦⠈⢿⣿⣿⣿⣷⣿⡆⠀\n⠘⠉⠋⠉⠉⠁⠀⠀⠀⠀⠀⠀⠀⠀⠀⠀⠀⠀⠀⠀⠀⠀⠀⠀⠀⠀⢠⣿⣿⣿⣿⣷⣿⢼⣿⣿⣿⣯⣿⣿⣎⡸⣿⡖⢴⣯⣧⠀\n⠀⠀⠀⠀⠀⠀⠀⠀⠄⠀⠀⠀⠀⠀⠀⠀⠀⠀⠀⠀⠀⠀⠀⠀⠀⣠⣾⣿⣽⣿⣿⣿⡿⠿⠿⠿⣿⣭⣽⣾⣿⣻⡜⠙⢝⣯⢻⡀\n⠀⠀⠀⠀⠀⠀⠀⠀⢂⣀⠀⠀⠀⠀⠀⠀⠀⠀⠀⢀⣤⣤⣴⣶⣿⣿⣿⣾⣿⣿⣿⣿⠇⠀⠀⠀⠈⠉⠀⠉⠉⠉⠿⠛⠶⢮⡟⣦\n⠀⠀⠀⠀⠀⠀⠀⠀⣿⣷⠄⠀⠀⠀⠀⠀⠀⠀⠀⠈⣿⡟⣯⣿⣿⣿⣿⣿⣿⣷⣿⣿⠀⠀⠀⠀⠀⠀⢀⡔⡶⡠⢤⣤⣯⠈⣿⡞\n⠀⠀⠀⠀⠀⠀⠀⠀⠉⣿⠀⠀⠀⠀⠀⠀⠀⠀⠀⠀⣿⡇⣿⣿⣿⣿⣿⣿⣿⣿⢾⡟⠀⠀⠀⠀⠀⠀⠀⠉⢰⠪⡘⣿⣽⡏⠌⢿\n⠀⠀⠀⠀⠀⠀⠀⠀⠀⣿⠴⠀⠀⠀⠀⠀⠀⠀⠀⠀⣿⡇⣿⣿⣿⣿⣿⣿⣿⣿⢽⡇⠀⠀⠀⠀⠀⠀⠀⠐⢘⣸⣟⣿⣿⣷⡇⢹\n⠀⠀⠀⠀⠀⠀⠀⠀⠀⢻⡇⡄⠀⠀⠀⠀⠀⠀⠀⠀⣿⣧⣿⣿⣿⣿⣿⣿⣿⣝⣿⡇⠀⠀⠀⠀⠀⠀⠀⠀⠈⠱⣿⣿⣿⣿⣧⠊\n⠀⠀⠀⠀⠀⠀⠀⠀⠀⠸⣷⢁⠀⠀⠀⠀⠀⠀⠀⢀⣿⣿⣿⣿⣿⣿⣿⣿⡿⣣⣿⠇⠀⠀⠀⠀⠀⠀⠀⠀⠀⠉⢿⡿⣿⣿⣿⣂\n⠀⠀⠀⠀⠀⠀⠀⠀⠀⠀⣿⡘⠀⠀⠀⠀⠀⠀⠀⢸⣿⢿⣿⣿⣿⣿⣿⣿⣿⡿⠁⠀⠀⠀⠀⠀⠀⠀⠀⠀⠀⠀⠀⠙⠻⢿⣿⣷\n⠀⠀⠀⠀⠀⠀⠀⠀⠀⠀⢸⣧⠂⠀⠀⠀⠀⠀⠀⣾⣿⣾⣿⣿⣿⣯⣷⠿⠋⠀⠀⠀⠀⠀⠀⠀⠀⠀⠀⠀⠀⠀⠀⠀⠀⠀⠈⠙",
    "runtimeUrl": "https://eikon.liftaris.dev/packages/liftaris/ares/blobs/sha256/23df2f6bba83c2db8ef580050b55e2f7a057122dbc5615639cf3377b008cbf49",
    "packageUrl": "https://eikon.liftaris.dev/packages/liftaris/ares/1.0.0.json",
    "detailUrl": "https://eikon.liftaris.dev/eikons/ares",
    "compatibility": {
      "eikon": ">=1 <2",
      "available": true
    },
    "trust": {
      "manifestDigest": "sha256:52c34c6122dab28aedfd3422eb211ba167cd52156e35f2c05669ab7c6b66b33d",
      "runtimeDigest": "sha256:23df2f6bba83c2db8ef580050b55e2f7a057122dbc5615639cf3377b008cbf49",
      "runtimeSize": 172082,
      "runtimeEncoding": "gzip",
      "runtimeDecodedSize": 1290412,
      "runtimeDecodedDigest": "sha256:f527b782d4fba18706faabbf681af43c8598bff1f5339bf4325f22a56be16bd6"
    }
  },
  {
    "kind": "eikon.catalog.entry",
    "schemaVersion": "1.0",
    "id": "liftaris/mono",
    "version": "1.0.0",
    "sourceKey": "registry:eikon.liftaris.dev:liftaris/mono@1.0.0",
    "name": "mono",
    "title": "mono",
    "author": "kaio",
    "glyph": "◐",
    "poster": "⠀⠀⠀⠀⠀⠀⠀⠀⠀⠀⠀⠀⠀⠀⠀⠀⠀⠀⠀⠀⠀⠀⠀⠀⠀⠀⠀⠀⠀⠀⠀⠀⠀⠀⠀⠀⠀⠀⠀⠀⠀⠀⠀⠀⠀⠀⠀⠀\n⠀⠀⠀⠀⠀⠀⠀⠀⠀⠀⠀⠀⠀⠀⠀⠀⠀⣀⣀⡀⠀⠀⠀⠀⠀⠀⠀⠀⠀⠀⠀⠀⠀⠀⠀⠀⠀⠀⠀⠀⠀⠀⠀⠀⠀⠀⠀⠀\n⠀⠀⠀⠀⠀⠀⠀⠀⠀⠀⠀⠀⠀⠀⣠⣴⣿⣿⣿⣿⣿⣶⣦⣄⣀⠀⠀⠀⠀⠀⠀⠀⠀⠀⠀⠀⠀⠀⠀⠀⠀⠀⠀⠀⠀⠀⠀⠀\n⠀⠀⠀⠀⠀⠀⠀⠀⠀⠀⠀⠀⠀⠈⣿⣿⣿⣿⣿⣿⣿⣿⣿⣿⣿⣿⣷⣦⣤⣀⠀⠀⠀⠀⠀⠀⠀⠀⠀⠀⠀⠀⠀⠀⠀⠀⠀⠀\n⠀⠀⠀⠀⠀⠀⠀⠀⠀⠀⠀⠀⠀⠐⣿⣿⣿⣿⣿⣿⣿⣿⣿⣿⣿⣿⣿⣿⣿⣿⣷⠀⠀⠀⠀⠀⠀⠀⠀⠀⠀⠀⠀⠀⠀⠀⠀⠀\n⠀⠀⠀⠀⠀⠀⠀⠀⠀⠀⠀⠀⠀⠈⣿⣿⣿⣿⣿⣿⣿⣿⣿⣿⣿⣿⣿⣿⣿⣿⣿⡄⠀⠀⠀⠀⠀⠀⠀⠀⠀⠀⠀⠀⠀⠀⠀⠀\n⠀⠀⠀⠀⠀⠀⠀⠀⠀⠀⠀⠀⠀⠘⣿⣿⣿⣿⣿⣿⣿⣿⣿⣿⣿⣿⣿⣿⣿⣿⣿⡇⠀⠀⠀⠀⠀⠀⠀⠀⠀⠀⠀⠀⠀⠀⠀⠀\n⠀⠀⠀⠀⠀⠀⠀⠀⠀⠀⠀⠀⠀⠀⣿⣿⣿⣿⣿⣿⣿⣿⣿⣿⣿⣿⣿⣿⣿⣿⣿⡇⠀⠀⠀⠀⠀⠀⠀⠀⠀⠀⠀⠀⠀⠀⠀⠀\n⠀⠀⠀⠀⠀⠀⠀⠀⠀⠀⠀⠀⠀⠀⣿⣿⣿⣿⣿⣿⣿⣿⣿⣿⣿⣿⣿⣿⣿⠟⢿⠃⠀⠀⠀⠀⠀⠀⠀⠀⠀⠀⠀⠀⠀⠀⠀⠀\n⠀⠀⠀⠀⠀⠀⠀⠀⠀⠀⠀⠀⠀⠀⣿⣿⣿⣿⣿⣿⣿⣿⣿⣿⣿⣿⣿⣏⢁⠰⣌⡄⠀⠀⠀⠀⠀⠀⠀⠀⠀⠀⠀⠀⠀⠀⠀⠀\n⠀⠀⠀⠀⠀⠀⠀⠀⠀⠀⠀⠀⠀⠀⣿⣿⣿⣿⣿⣿⣿⣿⣿⣿⣿⣿⣿⣿⡇⣡⣟⡇⠀⠀⠀⠀⠀⠀⠀⠀⠀⠀⠀⠀⠀⠀⠀⠀\n⠀⠀⠀⠀⠀⠀⠀⠀⠀⠀⠀⠀⠀⠀⣿⣿⣿⣿⣿⣿⣿⣿⣿⣿⣿⣿⣿⣿⣿⡿⠞⠀⠀⠀⠀⠀⠀⠀⠀⠀⠀⠀⠀⠀⠀⠀⠀⠀\n⠀⠀⠀⠀⠀⠀⠀⠀⠀⠀⠀⠀⠀⠀⣿⣿⣿⣿⣿⣿⣿⣿⣿⣿⣿⣿⣿⡏⠁⠁⠂⠀⠀⠀⠀⠀⠀⠀⠀⠀⠀⠀⠀⠀⠀⠀⠀⠀\n⠀⠀⠀⠀⠀⠀⠀⠀⠀⠀⠀⠀⠀⠀⣿⣿⣿⣿⣿⣿⣿⣿⣿⣿⣿⣿⣿⡇⢀⠁⠀⠀⠀⠀⠀⠀⠀⠀⠀⠀⠀⠀⠀⠀⠀⠀⠀⠀\n⠀⠀⠀⠀⠀⠀⠀⠀⠀⠀⠀⠀⠀⠀⣿⣿⡿⠟⠋⢉⠛⠻⠿⠿⠿⠿⢿⡥⠁⠁⠀⠀⠀⠀⠀⠀⠀⠀⠀⠀⠀⠀⠀⠀⠀⠀⠀⠀\n⠀⠀⠀⠀⠀⠀⠀⠀⠀⠀⠀⠀⠀⠀⠀⠁⠁⠁⠁⠥⠁⠁⠂⠁⠁⢀⣼⡇⢀⠀⠀⠀⠀⠀⠀⠀⠀⠀⠀⠀⠀⠀⠀⠀⠀⠀⠀⠀\n⠀⠀⠀⠀⠀⠀⠀⠀⠀⠀⠀⠀⠀⠀⠀⠀⠀⢸⣦⢀⢀⢀⠄⢀⢠⣾⣿⣥⣀⠀⠀⠀⠀⠀⠀⠀⠀⠀⠀⠀⠀⠀⠀⠀⠀⠀⠀⠀\n⠀⠀⠀⠀⠀⠀⠀⠀⠀⠀⠀⠀⠀⠀⠀⠀⠀⢸⣿⡇⢀⠂⠁⢀⣾⣿⣿⣿⣿⣦⡀⠀⠀⠀⠀⠀⠀⠀⠀⠀⠀⠀⠀⠀⠀⠀⠀⠀\n⠀⠀⠀⠀⠀⠀⠀⠀⠀⠀⠀⠀⠀⠀⠀⠀⠀⠘⣿⡇⠁⠁⢀⢸⣿⣿⣿⣿⣿⣿⣿⣦⣀⠀⠀⠀⠀⠀⠀⠀⠀⠀⠀⠀⠀⠀⠀⠀\n⠀⠀⠀⠀⠀⠀⠀⠀⠀⠀⠀⠀⠀⠀⠀⠀⢀⣠⣿⣇⣾⢀⣰⣿⣿⣿⣿⣿⣿⣿⣿⣿⣿⣿⣶⣤⡀⠀⠀⠀⠀⠀⠀⠀⠀⠀⠀⠀\n⠀⠀⠀⠀⠀⠀⠀⠀⠀⠀⠀⢀⣠⣴⣶⣿⣿⣿⣿⣿⣷⣿⣿⣿⣿⣿⣿⣿⣿⡿⣿⢿⠿⢟⡿⠿⠟⠓⠀⠀⠀⠀⠀⠀⠀⠀⠀⠀\n⠀⠀⠀⠀⠀⠀⠀⠀⠀⠀⠀⢸⣿⣿⣿⣿⣿⣿⣿⣿⣿⣿⣿⡿⠿⢟⠛⢉⢑⣀⢀⢉⠊⠉⢀⢀⠂⢀⠁⠀⠀⠀⠀⠀⠀⠀⠀⠀\n⠀⠀⠀⠀⠀⠀⠀⠀⠀⠀⠀⠀⠀⠉⠉⠛⠻⠛⠛⠛⠋⠉⠃⠂⠂⠁⠉⠁⠁⠁⠁⠁⠁⠁⠁⠁⠁⠁⠀⠀⠀⠀⠀⠀⠀⠀⠀⠀\n⠀⠀⠀⠀⠀⠀⠀⠀⠀⠀⠀⠀⠀⠀⠀⠀⠀⠀⠀⠀⠀⠀⠀⠀⠀⠀⠀⠀⠀⠀⠀⠀⠀⠀⠀⠀⠀⠀⠀⠀⠀⠀⠀⠀⠀⠀⠀⠀",
    "runtimeUrl": "https://eikon.liftaris.dev/packages/liftaris/mono/blobs/sha256/51577c51bf90641911392007cc3b138c2cfb3447ad5667204bd1c8be714183d8",
    "packageUrl": "https://eikon.liftaris.dev/packages/liftaris/mono/1.0.0.json",
    "detailUrl": "https://eikon.liftaris.dev/eikons/mono",
    "compatibility": {
      "eikon": ">=1 <2",
      "available": true
    },
    "trust": {
      "manifestDigest": "sha256:076b98be70632739b33517d336002562b9752ecb51e287d21abe073912fe3023",
      "runtimeDigest": "sha256:51577c51bf90641911392007cc3b138c2cfb3447ad5667204bd1c8be714183d8",
      "runtimeSize": 55621,
      "runtimeEncoding": "gzip",
      "runtimeDecodedSize": 1390777,
      "runtimeDecodedDigest": "sha256:44b52ecb76df67c638c44556aa002975c76d7df36a887b390a85e2d83076b862"
    }
  },
  {
    "kind": "eikon.catalog.entry",
    "schemaVersion": "1.0",
    "id": "liftaris/nous",
    "version": "1.0.0",
    "sourceKey": "registry:eikon.liftaris.dev:liftaris/nous@1.0.0",
    "name": "nous",
    "title": "nous",
    "author": "kaio",
    "glyph": "⬡",
    "poster": "⠀⠀⠀⠀⠀⠀⠀⠀⠀⠀⠀⠀⠀⠀⠀⠀⠀⠀⠀⢀⣀⣀⣠⣤⣤⣀⣀⣀⠀⠀⠀⠀⠀⠀⠀⠀⠀⠀⠀⠀⠀⠀⠀⠀⠀⠀⠀⠀\n⠀⠀⠀⠀⠀⠀⠀⠀⠀⠀⠀⠀⠀⢀⣀⣤⣤⣬⣥⣄⣀⠀⠉⠙⠻⣿⣿⣿⣿⣷⣶⣤⡀⠀⠀⠀⠀⠀⠀⠀⠀⠀⠀⠀⠀⠀⠀⠀\n⠀⠀⠀⠀⠀⠀⠀⠀⠀⠀⣀⣤⣾⣿⣿⣿⣿⣿⣿⣿⣿⣷⣦⡀⠀⠈⠻⣿⣿⣿⣿⣿⣿⣷⣄⠀⠀⠀⠀⠀⠀⠀⠀⠀⠀⠀⠀⠀\n⠀⠀⠀⠀⠀⠀⠀⢀⣤⣾⣿⣿⣿⣿⣿⣿⣿⣿⣿⣿⣿⣿⡿⡿⢦⡀⠀⠈⢿⣿⣿⣿⣿⣿⢿⡗⠄⠀⠀⠀⠀⠀⠀⠀⠀⠀⠀⠀\n⠀⠀⠀⠀⠀⠀⡰⣻⣿⣿⣿⢏⣿⣿⣿⣿⣿⣿⣿⡿⠙⠏⠀⠀⣮⡳⠀⠀⠈⢿⢿⠻⠿⡏⠁⠁⣸⣄⠀⠀⠀⠀⠀⠀⠀⠀⠀⠀\n⠀⠀⠀⠀⠀⠌⠈⠉⢺⠻⢃⠊⠙⠛⢠⡀⢀⠙⠁⠁⠀⡘⣶⣷⣿⣷⣾⠀⠀⠈⣶⣆⣳⣶⣮⢔⣿⣿⡆⠀⠀⠀⠀⠀⠀⠀⠀⠀\n⠀⠀⠀⠀⡼⣴⢶⣤⣶⣾⣼⣿⣿⣿⣿⢿⣿⣿⣿⣾⣶⣿⣿⣿⣿⣿⣿⡇⣀⣠⣸⣿⣷⣻⣿⣿⣿⣿⣷⡀⠀⠀⠀⠀⠀⠀⠀⠀\n⠀⠀⠀⢰⣿⣿⣿⣿⣿⣿⣿⣿⣿⣿⣿⡟⣿⣿⣿⣿⣿⣿⣿⣿⣿⣿⣿⣿⢯⣿⣚⣿⣿⣿⢿⣿⣿⣿⣿⣗⠀⠀⠀⠀⠀⠀⠀⠀\n⠀⠀⠀⢸⣿⣿⣿⣿⣿⣿⣿⢿⣿⣿⣿⣿⡘⣿⣿⣿⣿⣿⣿⣿⣿⣿⣿⣿⣿⣿⣿⣿⣿⣿⡿⣿⣿⣿⣿⣿⡄⠀⠀⠀⠀⠀⠀⠀\n⠀⠀⠀⢸⣿⣿⣿⣿⣿⣿⡿⠧⠻⠟⣻⠟⡓⠈⠛⠛⠛⠛⠛⠿⣿⣿⣿⣿⣿⣿⣿⣿⣿⣿⣿⣹⣿⣿⣿⣿⣇⠀⠀⠀⠀⠀⠀⠀\n⠀⠀⠀⠀⠻⣿⡿⣿⣿⣉⣁⠀⠀⠀⠀⠸⢻⣿⡷⢦⡄⠀⠀⠀⢹⣿⣿⣿⣿⢟⣛⡻⣿⣿⣿⣯⣿⣿⣿⣿⣿⡀⠀⠀⠀⠀⠀⠀\n⠀⠀⠀⠀⠀⠈⠙⠊⢻⣏⢿⠇⠀⠀⠀⠀⠬⠿⠥⠊⠀⠀⠀⠀⣿⣿⣿⣿⣿⣿⣿⣿⣿⣿⣿⣿⡼⣿⣿⣿⣿⣇⠀⠀⠀⠀⠀⠀\n⠀⠀⠀⠀⠀⠀⠀⠀⣸⣯⠊⠀⠀⠀⠀⠀⠀⠀⠀⠀⠀⠀⠀⠀⣿⣿⣿⣿⣿⣿⣿⣿⣿⣿⣿⣿⣷⢿⣿⣿⣿⣿⠀⠀⠀⠀⠀⠀\n⠀⠀⠀⠀⠀⠀⠀⠀⣿⡇⠠⠀⠀⠀⠀⠀⠀⠀⠀⠀⠀⠀⠀⢸⣿⣿⣿⣿⣿⣿⣿⣿⣿⣿⣿⣿⣿⡾⣿⣿⣿⣿⡇⠀⠀⠀⠀⠀\n⠀⠀⠀⠀⠀⠀⠀⠀⣿⣇⠰⣄⣄⡀⠀⠀⠀⠀⠀⠀⠀⠀⠀⣾⣿⣿⣿⣿⣿⣿⣿⣿⣿⣿⣿⣿⣿⣷⣿⣿⣿⣿⣿⡀⠀⠀⠀⠀\n⠀⠀⠀⠀⠀⠀⠀⢰⣿⣿⡆⠣⠄⠈⠁⠀⠀⠀⠀⠀⠀⠀⢠⣿⣿⣿⣿⠻⣿⣿⣿⣿⣿⣿⣿⣿⣿⣿⣼⣿⣿⢹⣿⣇⠀⠀⠀⠀\n⠀⠀⢠⠀⠀⠀⠀⢸⣿⣿⣿⣆⠀⠀⠀⠀⠀⠀⠀⠀⠀⠀⢸⣿⣿⣿⡏⢈⣿⣿⣿⣿⣿⣿⣿⣿⣿⣿⣿⣿⣿⠄⣿⣿⡀⠀⠀⠀\n⠀⠀⣟⠀⠀⠀⠀⣿⣿⣿⣿⣿⣦⣀⣀⣀⣀⣠⣄⡀⠀⠀⢸⣿⣿⣿⡾⠟⢿⣿⣿⣿⣿⣿⣿⣿⣿⣿⣿⣿⣿⠁⣹⣿⡇⠐⡄⠀\n⠀⢀⣿⣦⣀⣠⣼⣿⣿⣻⣿⣿⣿⣿⣿⣿⣿⣿⣿⣿⣄⠀⣸⣿⣿⣯⡀⣀⣼⣿⣿⣿⣿⣿⣿⣿⣿⣿⣿⣿⡿⢀⣿⣿⡇⠀⣷⠀\n⠀⠘⣜⠿⣿⣿⠿⠋⣱⣿⣿⣻⣿⣿⣿⣿⣿⣿⣿⣿⣿⡾⠋⢿⣿⣿⣿⣿⣿⣿⣿⣿⣿⣿⣿⣿⣿⣿⣿⣿⣣⣾⣿⣿⡇⢠⣿⠀\n⠀⠀⠙⠿⣶⣤⣶⣾⣿⣿⢋⣿⣿⣿⣿⣿⣿⣿⣿⠛⢋⡠⢆⠀⠙⠿⣿⣿⣿⣿⣿⣿⣿⣿⣿⣿⣿⣿⣿⣿⣿⣿⣿⡿⢠⣿⠏⠀\n⠀⠀⠀⠀⠀⠉⢯⣉⣉⣡⣾⣿⣿⣿⣿⣿⣿⣿⣿⣧⡀⢋⠝⠃⣀⣴⠟⠫⢛⣭⡿⠚⠋⠉⠁⠒⠫⣝⠻⣿⣿⣿⢟⣵⡿⠋⠀⠀\n⠀⠀⠀⠀⠀⠀⠈⠛⠿⠿⠛⢁⣿⣿⣿⣿⣿⣿⣿⣿⣷⣤⡶⠟⠉⠀⢀⣴⡟⠁⠀⠀⠀⠀⠀⠀⠀⠈⠳⣜⢿⡿⠟⠋⠀⠀⠀⠀\n⠀⠀⠀⠀⠀⠀⠀⠀⠀⠀⣠⣾⣿⣿⣿⣿⠿⣿⢯⡾⠋⠀⠀⢀⡔⠀⡾⠋⠀⠀⠀⠀⠀⠀⠀⠀⠀⠀⠀⠘⠮⠅⠀⠀⠀⠀⠀⠀",
    "runtimeUrl": "https://eikon.liftaris.dev/packages/liftaris/nous/blobs/sha256/6a74e9ae20ecafe6cf268230272582ef618b31927cd13e11ce59ed8931413883",
    "packageUrl": "https://eikon.liftaris.dev/packages/liftaris/nous/1.0.0.json",
    "detailUrl": "https://eikon.liftaris.dev/eikons/nous",
    "compatibility": {
      "eikon": ">=1 <2",
      "available": true
    },
    "trust": {
      "manifestDigest": "sha256:f0f49fb8a5baef97af50f31811c96061c5aa1cfdaea6987c8458d39e7bfe4ac3",
      "runtimeDigest": "sha256:6a74e9ae20ecafe6cf268230272582ef618b31927cd13e11ce59ed8931413883",
      "runtimeSize": 139822,
      "runtimeEncoding": "gzip",
      "runtimeDecodedSize": 1401439,
      "runtimeDecodedDigest": "sha256:b2685743b05ddf201920b69db58640d4fab644e637fa7d313c6dfa215fa41fb7"
    }
  },
  {
    "kind": "eikon.catalog.entry",
    "schemaVersion": "1.0",
    "id": "liftaris/ovo",
    "version": "1.0.0",
    "sourceKey": "registry:eikon.liftaris.dev:liftaris/ovo@1.0.0",
    "name": "ovo",
    "title": "ovo",
    "author": "kaio",
    "description": "Monochrome terminal avatar.",
    "glyph": "◆",
    "poster": "⠀⠀⠀⠀⠀⠀⠀⠀⠀⠀⠀⢀⣤⣾⣿⣿⣿⣿⣿⣿⣿⣿⣿⣿⣿⣿⣿⣿⣿⣿⣿⣿⣿⣿⣿⣿⣿⣿⣦⠉⠛⢷⣄⠀⠀⠀⠀⠀\n⠀⠀⠀⠀⠀⠀⠀⠀⠀⢤⣞⣿⣿⣿⣿⣿⣿⣿⣿⣿⣿⣿⣿⣿⣿⣿⣿⣿⣿⣿⣿⣿⣿⣷⠄⢙⣿⣿⣿⡧⠀⠀⠹⣇⠀⠀⠀⠀\n⠀⠀⠀⠀⢀⣠⡴⠶⠟⠛⠛⠉⠉⠉⠉⠉⠛⠛⠿⢿⣿⣿⣷⣾⣽⣻⢿⣿⣿⣿⡿⡿⣿⣿⣦⠀⠹⣿⣿⣿⡄⠀⠀⢻⠀⠀⠀⠀\n⠀⠀⠀⣰⠟⠁⠀⠀⠀⠀⠀⠀⠀⠀⠀⠀⠀⠀⠀⠀⠈⠙⠛⠿⣿⣿⣿⣮⣟⠿⣿⣮⡊⠻⠭⠅⠀⠨⣿⣿⣿⡄⠀⠘⣇⠀⠀⠀\n⠀⠀⣰⠏⠀⠀⠀⠀⠀⠀⠀⠀⠀⠀⠀⠀⠀⠀⠀⠀⠀⠀⠀⠀⠈⠙⠿⣿⣿⣷⣮⡛⢷⡀⠈⠀⠀⠀⠈⢿⣿⣿⡄⠀⠹⡄⠀⠀\n⠀⢠⡏⠀⠀⠀⡠⣦⣀⠀⠀⠀⠀⢀⠀⡀⢀⢀⠀⢀⢀⠀⣠⡄⣀⣤⠄⠈⠛⢿⣿⣿⣦⡉⠄⠀⠀⠀⠀⠈⢻⣿⣿⡄⠀⢧⠀⠀\n⠀⢸⠁⠀⠀⠐⢮⣻⣿⣷⡀⢀⢰⡌⣾⢼⣧⣾⣵⣿⡵⣺⣿⣾⡿⠋⠂⠀⠀⠀⠙⢿⣿⣿⣦⡀⠀⠀⠀⠀⠈⠻⣿⣿⣆⠘⡄⠀\n⠀⣼⠀⠀⠀⠀⠀⠀⢹⣿⣿⡼⣟⣿⡿⣾⣻⣿⣯⣿⣿⣿⡿⠛⢁⣀⣤⣤⣤⣀⠀⠀⠉⠻⣿⣿⣦⡀⠀⠀⠀⠈⢺⣿⣿⣆⢁⠀\n⠀⡟⠀⠀⠀⠀⠀⣼⣦⠹⣿⣿⣿⣯⣯⢿⣿⣾⣿⣿⠿⠉⠀⠀⠉⠉⠉⠙⠛⠿⣖⠄⠀⠀⠘⢿⣿⣿⣄⠀⠀⠀⠀⠓⠺⣿⣆⠀\n⠀⡇⠀⠀⠀⠀⢰⣿⠏⠀⣉⢿⣿⣿⣻⣿⣿⣿⡿⠁⠀⠀⠀⠀⠘⠃⠀⢰⣤⠀⣤⣶⣴⣤⠀⠀⠹⣿⣿⣧⡀⠀⠀⠀⠀⢹⣿⣆\n⠀⡇⠀⠀⠀⠀⢼⣿⣟⢰⠉⠈⢻⣿⣿⣿⣿⣟⣆⠀⠀⠀⢸⣧⣀⠀⣀⣼⡟⢠⣿⣿⣿⣿⣤⠀⠀⠘⢿⣿⣷⡀⠀⠀⠀⠈⢿⣿\n⢀⡇⠀⠀⠀⠀⣸⣿⣿⡜⣷⣄⣿⡟⢻⢿⣿⣿⣿⣷⣦⣄⠠⣙⠻⠿⠟⣋⣴⣿⣿⣿⣿⣿⠏⠀⠀⠀⠈⢿⣿⣷⡀⠀⠀⠀⠀⠊\n⢸⡇⠀⠀⠀⠀⢾⣿⣿⣿⣆⣼⡿⣠⡔⢫⣿⣿⣿⣿⣿⣿⣿⣾⣿⣿⣿⣿⣿⣿⣿⣿⣿⡟⠛⠀⠀⠀⠀⠈⢿⣿⣷⠀⠀⠀⠀⠀\n⢸⠃⠀⠀⠀⠀⣸⣿⣿⡯⣾⣿⢃⣿⠃⠑⠾⣽⣿⣿⣿⣿⣿⣿⣿⣿⣿⣿⣿⣿⣿⡿⢿⠎⠀⢠⣰⠁⠀⠀⠘⣿⣿⡇⠀⠀⠀⢀\n⣿⠀⠀⠀⠀⠐⣡⣿⣿⣿⢿⠿⢸⣿⠀⠀⠀⠱⠻⠛⠚⠉⣉⣁⣁⣑⣛⢿⣿⣿⡟⠿⢀⢀⣾⠿⠊⠀⠀⠀⠀⢹⡅⠁⠀⠀⠀⠨\n⡏⠀⠀⠀⠀⠐⡽⡛⣻⣧⣴⣤⡈⣟⠀⠀⠀⢀⣠⣴⣾⣿⣿⣿⣿⣿⣿⣿⣿⣾⣶⣾⣿⣿⣿⢤⠦⠂⠀⠀⠀⣿⢄⡃⠀⠀⠀⠀\n⡇⠀⠀⠀⠀⠀⠠⡻⣿⣿⣿⣿⣿⡽⡀⢀⣴⣿⣿⣿⣿⣿⡿⣻⡟⠛⣻⣏⢈⣿⢌⠻⢯⠙⠛⠀⠀⠀⠀⠀⢠⡟⠋⠁⠀⠀⠀⣠\n⡇⠀⠀⠀⠀⠀⢀⡌⣹⡷⢛⣿⣿⣿⣦⣸⣿⣿⢟⣿⡾⣫⠿⠃⡤⣶⣏⠛⠀⠙⠀⠁⠀⠀⠀⠀⣀⠴⠁⢀⡾⠁⠀⠀⠀⠀⠀⠁\n⠹⣦⣀⠀⠀⠀⠘⢷⣿⡆⣩⢉⢿⣿⣿⡿⣛⣶⠟⣩⣐⡴⠀⣧⣀⣼⣿⣷⣬⡶⠈⠀⢀⣠⣴⢞⠃⢀⣴⠟⠁⠀⠀⠀⠀⠀⠀⢀\n⠀⠈⠻⣷⣦⣄⠀⠘⠻⣿⣿⡅⣊⢸⠛⣵⠟⢀⡈⣴⣿⣿⣼⣿⣿⣿⠟⠘⠋⣀⣤⣶⣿⣿⣹⡴⠾⠋⠁⠀⠀⠀⠀⠀⠠⠐⠚⠉\n⠀⠀⠀⠀⣙⢿⣷⣤⠀⠋⢿⣿⣿⣦⡆⢁⢠⣿⣿⣿⡿⢹⣿⡏⡿⠁⣀⣴⣾⣿⣿⠿⠛⠋⠁⠀⠀⠀⠀⠀⠀⢀⣀⡤⠐⠀⠀⠀\n⠀⠀⠀⢰⣿⡄⠙⢿⣷⡄⠈⠋⣿⣿⣷⣼⣿⣿⢿⣿⡴⠉⠟⠀⣠⣾⣿⠿⠋⠉⠀⠀⠀⠀⠀⠀⣀⣠⣴⣶⡟⠋⠁⠀⠀⠀⠀⠀\n⠀⠀⠀⠈⢿⣷⡀⠀⠙⢿⣦⡀⠘⠘⣿⢿⣿⣡⠀⠟⠁⠀⣠⣾⠟⠉⠀⠀⣀⠀⠀⠀⢀⣠⣦⣿⣿⠿⠛⠁⠀⠀⠀⣀⣠⠰⠂⠀\n⠀⠀⢠⡞⠀⠻⢿⣄⠀⠀⠻⣷⡄⠀⠈⠘⠁⠙⠁⠀⢠⡾⠋⠀⢀⡤⠖⢋⣠⣤⣶⣾⣿⠿⠛⠉⠀⠀⢀⣠⣴⡾⠟⠋⠁⠀⠀⠀",
    "runtimeUrl": "https://eikon.liftaris.dev/packages/liftaris/ovo/blobs/sha256/7eea1d34fedcfd8fc13a828bf5349f73fe3a6e0073f1adb9ee021ec5c75c3b51",
    "packageUrl": "https://eikon.liftaris.dev/packages/liftaris/ovo/1.0.0.json",
    "detailUrl": "https://eikon.liftaris.dev/eikons/ovo",
    "compatibility": {
      "eikon": ">=1 <2",
      "available": true
    },
    "trust": {
      "manifestDigest": "sha256:8aa53fdd0fc920055ed1b711801cafae63a0f6e09c8de7717ef7549118f43a2c",
      "runtimeDigest": "sha256:7eea1d34fedcfd8fc13a828bf5349f73fe3a6e0073f1adb9ee021ec5c75c3b51",
      "runtimeSize": 133601,
      "runtimeEncoding": "gzip",
      "runtimeDecodedSize": 1376292,
      "runtimeDecodedDigest": "sha256:3f78134ff65148a6917da7adc33b6093cfa740c90fbc3c310a781d19f5ce7da5"
    }
  }
]
